application_example/__init__.py
application_example/example.py
keepcodingtest_jonas-0.0.7.dist-info/METADATA
keepcodingtest_jonas-0.0.7.dist-info/WHEEL
keepcodingtest_jonas-0.0.7.dist-info/top_level.txt
keepcodingtest_jonas-0.0.7.dist-info/RECORD
