Metadata-Version: 2.1
Name: keepcodingtest-jonas
Version: 0.0.7
Summary: Simple Example
Author: jonasmarquez
Author-email: jonas@jonasmarquez.com
License: UNKNOWN
Platform: UNKNOWN
Requires-Python: >=3.6
Requires-Dist: build
Requires-Dist: twine
Requires-Dist: coloredlogs
